mcp/__init__.py
mcp/py.typed
mcp/types.py
mcp/cli/__init__.py
mcp/cli/claude.py
mcp/cli/cli.py
mcp/client/__init__.py
mcp/client/__main__.py
mcp/client/session.py
mcp/client/sse.py
mcp/client/websocket.py
mcp/client/stdio/__init__.py
mcp/client/stdio/win32.py
mcp/server/__init__.py
mcp/server/__main__.py
mcp/server/models.py
mcp/server/session.py
mcp/server/sse.py
mcp/server/stdio.py
mcp/server/streaming_asgi_transport.py
mcp/server/websocket.py
mcp/server/auth/__init__.py
mcp/server/auth/errors.py
mcp/server/auth/json_response.py
mcp/server/auth/provider.py
mcp/server/auth/routes.py
mcp/server/auth/settings.py
mcp/server/auth/handlers/__init__.py
mcp/server/auth/handlers/authorize.py
mcp/server/auth/handlers/metadata.py
mcp/server/auth/handlers/register.py
mcp/server/auth/handlers/revoke.py
mcp/server/auth/handlers/token.py
mcp/server/auth/middleware/__init__.py
mcp/server/auth/middleware/auth_context.py
mcp/server/auth/middleware/bearer_auth.py
mcp/server/auth/middleware/client_auth.py
mcp/server/fastmcp/__init__.py
mcp/server/fastmcp/exceptions.py
mcp/server/fastmcp/server.py
mcp/server/fastmcp/prompts/__init__.py
mcp/server/fastmcp/prompts/base.py
mcp/server/fastmcp/prompts/manager.py
mcp/server/fastmcp/prompts/prompt_manager.py
mcp/server/fastmcp/resources/__init__.py
mcp/server/fastmcp/resources/base.py
mcp/server/fastmcp/resources/resource_manager.py
mcp/server/fastmcp/resources/templates.py
mcp/server/fastmcp/resources/types.py
mcp/server/fastmcp/tools/__init__.py
mcp/server/fastmcp/tools/base.py
mcp/server/fastmcp/tools/tool_manager.py
mcp/server/fastmcp/utilities/__init__.py
mcp/server/fastmcp/utilities/func_metadata.py
mcp/server/fastmcp/utilities/logging.py
mcp/server/fastmcp/utilities/types.py
mcp/server/lowlevel/__init__.py
mcp/server/lowlevel/helper_types.py
mcp/server/lowlevel/server.py
mcp/shared/__init__.py
mcp/shared/auth.py
mcp/shared/context.py
mcp/shared/exceptions.py
mcp/shared/memory.py
mcp/shared/progress.py
mcp/shared/session.py
mcp_custom_2-1.7.2.dist-info/METADATA
mcp_custom_2-1.7.2.dist-info/WHEEL
mcp_custom_2-1.7.2.dist-info/entry_points.txt
mcp_custom_2-1.7.2.dist-info/licenses/LICENSE
mcp_custom_2-1.7.2.dist-info/RECORD
