Metadata-Version: 2.4
Name: mcp-custom-2
Version: 1.7.2
Summary: Custom fork of the Model Context Protocol SDK - 2
Author: Anthropic, PBC.
Maintainer-email: David Soria Parra <davidsp@anthropic.com>, Justin Spahr-Summers <justin@anthropic.com>
License: MIT
License-File: LICENSE
Keywords: automation,git,llm,mcp
Classifier: Development Status :: 4 - Beta
Classifier: Intended Audience :: Developers
Classifier: License :: OSI Approved :: MIT License
Classifier: Programming Language :: Python :: 3
Classifier: Programming Language :: Python :: 3.10
Classifier: Programming Language :: Python :: 3.11
Classifier: Programming Language :: Python :: 3.12
Requires-Python: >=3.10
Requires-Dist: anyio>=4.5
Requires-Dist: httpx-sse>=0.4
Requires-Dist: httpx>=0.27
Requires-Dist: pydantic-settings>=2.5.2
Requires-Dist: pydantic<3.0.0,>=2.7.2
Requires-Dist: sse-starlette>=1.6.1
Requires-Dist: starlette>=0.27
Requires-Dist: uvicorn>=0.23.1; sys_platform != 'emscripten'
Provides-Extra: cli
Requires-Dist: python-dotenv>=1.0.0; extra == 'cli'
Requires-Dist: typer>=0.12.4; extra == 'cli'
Provides-Extra: rich
Requires-Dist: rich>=13.9.4; extra == 'rich'
Provides-Extra: ws
Requires-Dist: websockets>=15.0.1; extra == 'ws'
